posix_compat/__init__.py
posix_compat/cli.py
posix_compat/core.py
posix_compat/gui.py
posix_compat/i18n.py
posix_compat/ollama_client.py
posix_compat-0.1.3.dist-info/licenses/LICENSE
posix_compat-0.1.3.dist-info/METADATA
posix_compat-0.1.3.dist-info/WHEEL
posix_compat-0.1.3.dist-info/entry_points.txt
posix_compat-0.1.3.dist-info/top_level.txt
posix_compat-0.1.3.dist-info/RECORD
