Metadata-Version: 2.4
Name: posix-compat
Version: 0.1.3
Summary: A cross-platform POSIX compatibility layer with CLI and GUI
Author-email: Wedonotuse <wedonotuse@outlook.com>
Project-URL: Homepage, https://github.com/cycleuser/POSIX-Compatibility-Layer
Classifier: Programming Language :: Python :: 3
Classifier: License :: OSI Approved :: GNU General Public License v3 (GPLv3)
Classifier: Operating System :: OS Independent
Requires-Python: >=3.7
License-File: LICENSE
Dynamic: license-file
